pywebdavserver/__init__.py
pywebdavserver/_version.py
pywebdavserver/cli.py
pywebdavserver/cli_config.py
pywebdavserver/config.py
pywebdavserver/constants.py
pywebdavserver/obscure.py
pywebdavserver/provider.py
pywebdavserver/server.py
pywebdavserver/providers/__init__.py
pywebdavserver/providers/drime.py
pywebdavserver/providers/local.py
pywebdavserver-0.1.2.dist-info/licenses/LICENSE
pywebdavserver-0.1.2.dist-info/METADATA
pywebdavserver-0.1.2.dist-info/WHEEL
pywebdavserver-0.1.2.dist-info/entry_points.txt
pywebdavserver-0.1.2.dist-info/top_level.txt
pywebdavserver-0.1.2.dist-info/RECORD
