Metadata-Version: 2.4
Name: pywebdavserver
Version: 0.1.2
Summary: WebDAV server with pluggable storage backends (local filesystem, Drime Cloud)
Author-email: Holger Nahrstaedt <nahrstaedt@gmail.com>
License: MIT License
Project-URL: Homepage, https://github.com/holgern/pywebdavserver
Classifier: Intended Audience :: Developers
Classifier: License :: OSI Approved :: MIT License
Classifier: Operating System :: OS Independent
Classifier: Programming Language :: Python :: 3
Classifier: Programming Language :: Python :: 3.9
Classifier: Programming Language :: Python :: 3.10
Classifier: Programming Language :: Python :: 3.11
Classifier: Programming Language :: Python :: 3.12
Classifier: Programming Language :: Python :: 3.13
Classifier: Programming Language :: Python :: 3.14
Classifier: Topic :: Software Development :: Libraries
Requires-Python: >=3.9
License-File: LICENSE
Requires-Dist: click>=8.0.0
Requires-Dist: cheroot>=9.0
Requires-Dist: wsgidav>=4.0.0
Requires-Dist: rich>=13.0.0
Requires-Dist: vaultconfig
Provides-Extra: drime
Requires-Dist: pydrime>=0.1.0; extra == "drime"
Provides-Extra: dev
Requires-Dist: pytest>=7.0.0; extra == "dev"
Requires-Dist: ruff>=0.1.0; extra == "dev"
Dynamic: license-file
